MANIFEST.in
README.md
flydra_fastfinder_help.c
flydra_fastfinder_help.pyx
pyproject.toml
setup.py
flydra_analysis/__init__.py
flydra_analysis/image_compare.py
flydra_analysis/kalmanize.py
flydra_analysis/mpl_markersize.py
flydra_analysis/offline_data_save.py
flydra_analysis/talign.py
flydra_analysis/test_commands.py
flydra_analysis/test_geom.py
flydra_analysis/test_reconstruction.py
flydra_analysis/version.py
flydra_analysis.egg-info/PKG-INFO
flydra_analysis.egg-info/SOURCES.txt
flydra_analysis.egg-info/dependency_links.txt
flydra_analysis.egg-info/entry_points.txt
flydra_analysis.egg-info/requires.txt
flydra_analysis.egg-info/top_level.txt
flydra_analysis/a2/Makefile.kalmanize
flydra_analysis/a2/__init__.py
flydra_analysis/a2/aggdraw_coord_shifter.py
flydra_analysis/a2/analysis_options.py
flydra_analysis/a2/auto_discover_movies.py
flydra_analysis/a2/auto_discover_ufmfs.py
flydra_analysis/a2/benu.py
flydra_analysis/a2/benu_colormaps.py
flydra_analysis/a2/calculate_reprojection_errors.py
flydra_analysis/a2/calculate_skipped_frames.py
flydra_analysis/a2/calibration_align_gui.py
flydra_analysis/a2/calibration_to_xml.py
flydra_analysis/a2/check_clock_sync.py
flydra_analysis/a2/check_frame_skip.py
flydra_analysis/a2/check_mainbrain_h5_contiguity.py
flydra_analysis/a2/conditions.py
flydra_analysis/a2/conditions2.py
flydra_analysis/a2/conditions_draw.py
flydra_analysis/a2/core_analysis.py
flydra_analysis/a2/data2smoothed.py
flydra_analysis/a2/densities.py
flydra_analysis/a2/experiment_layout.py
flydra_analysis/a2/find_equiv_obj_id.py
flydra_analysis/a2/find_long_trajectories.py
flydra_analysis/a2/flydra_images_export.py
flydra_analysis/a2/flydra_scons.py
flydra_analysis/a2/flydra_textlog2csv.py
flydra_analysis/a2/flypos.py
flydra_analysis/a2/get_2D_image_latency.py
flydra_analysis/a2/get_2D_image_latency_plot.py
flydra_analysis/a2/get_clock_sync.py
flydra_analysis/a2/h5_info.py
flydra_analysis/a2/h5_shorten.py
flydra_analysis/a2/image_based_orientation.py
flydra_analysis/a2/kdmovie_saver.py
flydra_analysis/a2/kdmovie_saver_default_path.kmp
flydra_analysis/a2/kdviewer.py
flydra_analysis/a2/lsprofcalltree.py
flydra_analysis/a2/misc.py
flydra_analysis/a2/missing_value_error.py
