Metadata-Version: 2.1
Name: flydra-analysis
Version: 0.7.17
Summary: flydra analysis tools
Author-email: Andrew Straw <strawman@astraw.com>
Maintainer-email: Andrew Straw <strawman@astraw.com>
Project-URL: homepage, https://github.com/strawlab/flydra
Requires-Python: >=3.8
Requires-Dist: setuptools>=44.1
Requires-Dist: numpy>=1.19
Requires-Dist: cython>=0.26
Requires-Dist: cgkit1>=1.3.0
Requires-Dist: flydra_core
Requires-Dist: pytest
Requires-Dist: pycairo
Requires-Dist: matplotlib
Requires-Dist: multicamselfcal>=0.3.0
Requires-Dist: pymvg>=2.1.0
Requires-Dist: progressbar
Requires-Dist: motmot.FlyMovieFormat
Requires-Dist: motmot.ufmf
Requires-Dist: motmot.imops
Requires-Dist: h5py
Requires-Dist: pandas
Requires-Dist: traits
Requires-Dist: traitsui
Requires-Dist: pillow
Requires-Dist: aggdraw
Requires-Dist: PyYAML
Requires-Dist: sympy
Requires-Dist: cherrypy
